{
	"coin": {
		"admin": {
			"form": {
				"labels": {
					"tokenErc20": "\ud1a0\ud070Erc20",
					"duration": "\uc9c0\uc18d",
					"bonusTokenFraction": "\ubcf4\ub108\uc2a4\ud1a0\ud070\ubd84\uc218",
					"popularToken": "\uc778\uae30\ud1a0\ud070",
					"donations": "\uae30\ubd80",
					"rewardsRateFraction": "\ubcf4\uc0c1\ube44\uc728\ubd84\uc218",
					"numerator": "\ubd84\uc790",
					"denominator": "\ubd84\ubaa8"
				},
				"small": {
					"tokenErc20": "\ud1a0\ud070Erc20",
					"duration": "\uae30\uac04(\uc77c)",
					"bonusTokenFraction": "\ubcf4\ub108\uc2a4\ud1a0\ud070\ubd84\uc218",
					"popularToken": "\uc778\uae30\ud1a0\ud070",
					"donations": "\uae30\ubd80",
					"rewardsRateFraction": "\ubcf4\uc0c1\ube44\uc728\ubd84\uc218",
					"numerator": "\ubd84\uc790",
					"denominator": "\ubd84\ubaa8"
				}
			},
			"placeholders": {
				"optional": "(\uc120\ud0dd \uacfc\ubaa9)",
				"tuple": "\ud29c\ud50c[]",
				"number": "\uc22b\uc790",
				"address": "\uc8fc\uc18c",
				"fraction": "\ubd84\uc218",
				"integer": "\uc815\uc218",
				"seconds": "\ucd08",
				"days": "\ub0a0",
				"uint256": "\ub2e8\uc704256",
				"uint192": "\ub2e8\uc704192",
				"uint64": "\ub2e8\uc70464",
				"uint32": "uint32",
				"uint16": "\ub2e8\uc70416"
			},
			"errmsgs": {
				"ThereAreNoPools": "\uc218\uc601\uc7a5\uc774 \uc5c6\uc2b5\ub2c8\ub2e4."
			},
			"btns": {
				"createPool": "\ud480 \uc0dd\uc131",
				"createPoolInForm": "\ub9cc\ub4e4\ub2e4"
			},
			"createPool": "\ud480 \uc0dd\uc131",
			"produce": "\uc0dd\uc0b0\ud558\ub2e4",
			"loading": "\ub85c\ub4dc \uc911",
			"viewInstancesList": "\uc0c8\ub85c \uace0\uce68 \ubaa9\ub85d"
		}
	}
}